LICENCE
elicito-0.7.0.dist-info/METADATA
elicito-0.7.0.dist-info/WHEEL
elicito-0.7.0.dist-info/entry_points.txt
elicito-0.7.0.dist-info/licenses/LICENCE
elicito/__init__.py
elicito/_checks.py
elicito/_outputs.py
elicito/elicit.py
elicito/exceptions.py
elicito/initialization.py
elicito/losses.py
elicito/networks.py
elicito/optimization.py
elicito/plots.py
elicito/py.typed
elicito/simulations.py
elicito/targets.py
elicito/types.py
elicito/utils.py
elicito-0.7.0.dist-info/RECORD
