Metadata-Version: 2.1
Name: elicito
Version: 0.7.0
Summary: A Python package for learning prior distributions based on expert knowledge
Author-Email: Florence Bockting <florence.bockting@tu-dortmund.de>
License: Apache-2.0
Classifier: Development Status :: 3 - Alpha
Classifier: Intended Audience :: Science/Research
Classifier: License :: OSI Approved :: Apache Software License
Classifier: Natural Language :: English
Classifier: Operating System :: OS Independent
Classifier: Programming Language :: Python
Classifier: Programming Language :: Python :: 3
Classifier: Programming Language :: Python :: 3 :: Only
Classifier: Programming Language :: Python :: 3.11
Classifier: Programming Language :: Python :: 3.12
Classifier: Programming Language :: Python :: 3.13
Classifier: Typing :: Typed
Project-URL: Homepage, https://elicito.readthedocs.io
Project-URL: Documentation, https://elicito.readthedocs.io
Project-URL: Changelog, https://elicito.readthedocs.io/en/stable/changelog
Project-URL: Repository, https://github.com/florence-bockting/elicito
Project-URL: Issues, https://github.com/florence-bockting/elicito/issues
Requires-Python: <3.14,>=3.11
Requires-Dist: tqdm>=4.38
Requires-Dist: numpy>=1.24
Requires-Dist: tensorflow>=2.16.0
Requires-Dist: tensorflow-probability>=0.24.0
Requires-Dist: joblib>=1.4.2
Requires-Dist: tf-keras>=2.16.0
Requires-Dist: xarray>=2025.9.0
Provides-Extra: plots
Requires-Dist: matplotlib>=3.7.1; extra == "plots"
Requires-Dist: arviz_stats>=0.6.0; extra == "plots"
Provides-Extra: pandas
Requires-Dist: pandas>=2.2.3; extra == "pandas"
Provides-Extra: scipy
Requires-Dist: scipy>=1.14.0; extra == "scipy"
Provides-Extra: full
Requires-Dist: elicito[plots]; extra == "full"
Requires-Dist: elicito[pandas]; extra == "full"
Requires-Dist: elicito[scipy]; extra == "full"
Provides-Extra: locked
Requires-Dist: absl-py==2.3.1; extra == "locked"
Requires-Dist: astunparse==1.6.3; extra == "locked"
Requires-Dist: attrs==24.3.0; extra == "locked"
Requires-Dist: certifi==2024.12.14; extra == "locked"
Requires-Dist: charset-normalizer==3.4.1; extra == "locked"
Requires-Dist: cloudpickle==3.1.2; extra == "locked"
Requires-Dist: colorama==0.4.6; extra == "locked"
Requires-Dist: decorator==5.1.1; extra == "locked"
Requires-Dist: dm-tree==0.1.9; extra == "locked"
Requires-Dist: flatbuffers==25.9.23; extra == "locked"
Requires-Dist: gast==0.6.0; extra == "locked"
Requires-Dist: google-pasta==0.2.0; extra == "locked"
Requires-Dist: grpcio==1.76.0; extra == "locked"
Requires-Dist: h5py==3.15.1; extra == "locked"
Requires-Dist: idna==3.10; extra == "locked"
Requires-Dist: joblib==1.5.2; extra == "locked"
Requires-Dist: keras==3.12.0; extra == "locked"
Requires-Dist: libclang==18.1.1; extra == "locked"
Requires-Dist: markdown==3.7; extra == "locked"
Requires-Dist: markdown-it-py==3.0.0; extra == "locked"
Requires-Dist: markupsafe==3.0.2; extra == "locked"
Requires-Dist: mdurl==0.1.2; extra == "locked"
Requires-Dist: ml-dtypes==0.5.3; extra == "locked"
Requires-Dist: namex==0.1.0; extra == "locked"
Requires-Dist: numpy==2.3.4; extra == "locked"
Requires-Dist: opt-einsum==3.4.0; extra == "locked"
Requires-Dist: optree==0.17.0; extra == "locked"
Requires-Dist: packaging==24.2; extra == "locked"
Requires-Dist: pandas==2.3.3; extra == "locked"
Requires-Dist: pillow==12.0.0; extra == "locked"
Requires-Dist: protobuf==6.33.0; extra == "locked"
Requires-Dist: pygments==2.19.1; extra == "locked"
Requires-Dist: python-dateutil==2.9.0.post0; extra == "locked"
Requires-Dist: pytz==2025.2; extra == "locked"
Requires-Dist: requests==2.32.3; extra == "locked"
Requires-Dist: rich==14.2.0; extra == "locked"
Requires-Dist: setuptools==75.6.0; extra == "locked"
Requires-Dist: six==1.17.0; extra == "locked"
Requires-Dist: tensorboard==2.20.0; extra == "locked"
Requires-Dist: tensorboard-data-server==0.7.2; extra == "locked"
Requires-Dist: tensorflow==2.20.0; extra == "locked"
Requires-Dist: tensorflow-probability==0.25.0; extra == "locked"
Requires-Dist: termcolor==3.2.0; extra == "locked"
Requires-Dist: tf-keras==2.20.1; extra == "locked"
Requires-Dist: tqdm==4.67.1; extra == "locked"
Requires-Dist: typing-extensions==4.12.2; extra == "locked"
Requires-Dist: tzdata==2025.2; extra == "locked"
Requires-Dist: urllib3==2.3.0; extra == "locked"
Requires-Dist: werkzeug==3.1.3; extra == "locked"
Requires-Dist: wheel==0.45.1; extra == "locked"
Requires-Dist: wrapt==2.0.1; extra == "locked"
Requires-Dist: xarray==2025.10.1; extra == "locked"
Provides-Extra: plots-locked
Requires-Dist: arviz-stats==0.7.0; extra == "plots-locked"
Requires-Dist: contourpy==1.3.3; extra == "plots-locked"
Requires-Dist: cycler==0.12.1; extra == "plots-locked"
Requires-Dist: fonttools==4.60.1; extra == "plots-locked"
Requires-Dist: kiwisolver==1.4.9; extra == "plots-locked"
Requires-Dist: matplotlib==3.10.7; extra == "plots-locked"
Requires-Dist: numpy==2.3.4; extra == "plots-locked"
Requires-Dist: packaging==24.2; extra == "plots-locked"
Requires-Dist: pillow==12.0.0; extra == "plots-locked"
Requires-Dist: pyparsing==3.2.5; extra == "plots-locked"
Requires-Dist: python-dateutil==2.9.0.post0; extra == "plots-locked"
Requires-Dist: scipy==1.16.3; extra == "plots-locked"
Requires-Dist: six==1.17.0; extra == "plots-locked"
Provides-Extra: pandas-locked
Requires-Dist: numpy==2.3.4; extra == "pandas-locked"
Requires-Dist: pandas==2.3.3; extra == "pandas-locked"
Requires-Dist: python-dateutil==2.9.0.post0; extra == "pandas-locked"
Requires-Dist: pytz==2025.2; extra == "pandas-locked"
Requires-Dist: six==1.17.0; extra == "pandas-locked"
Requires-Dist: tzdata==2025.2; extra == "pandas-locked"
Provides-Extra: scipy-locked
Requires-Dist: numpy==2.3.4; extra == "scipy-locked"
Requires-Dist: scipy==1.16.3; extra == "scipy-locked"
Provides-Extra: full-locked
Requires-Dist: arviz-stats==0.7.0; extra == "full-locked"
Requires-Dist: contourpy==1.3.3; extra == "full-locked"
Requires-Dist: cycler==0.12.1; extra == "full-locked"
Requires-Dist: fonttools==4.60.1; extra == "full-locked"
Requires-Dist: kiwisolver==1.4.9; extra == "full-locked"
Requires-Dist: matplotlib==3.10.7; extra == "full-locked"
Requires-Dist: numpy==2.3.4; extra == "full-locked"
Requires-Dist: packaging==24.2; extra == "full-locked"
Requires-Dist: pandas==2.3.3; extra == "full-locked"
Requires-Dist: pillow==12.0.0; extra == "full-locked"
Requires-Dist: pyparsing==3.2.5; extra == "full-locked"
Requires-Dist: python-dateutil==2.9.0.post0; extra == "full-locked"
Requires-Dist: pytz==2025.2; extra == "full-locked"
Requires-Dist: scipy==1.16.3; extra == "full-locked"
Requires-Dist: six==1.17.0; extra == "full-locked"
Requires-Dist: tzdata==2025.2; extra == "full-locked"
